LAB3/4/l3q4.v
module l3q4(A,B,C,D,f);
input A,B,C,D;
output f;
wire o1,o2,o3;
nand(d,D,D);
nand(o1,A,D);
nand(o2,B,d);
nand(o3,o1,o2);
nand(f,o3,o3);
endmodule

LAB3/4/l3q4_tb.v
`timescale 1ns/1ns
`include "l3q4.v"

module l3q4_tb; // Add this line to define the testbench module
  reg A, B, C, D;    // Inputs
  wire f;             // Output
  l3q4 uut(A,B,C,D,f);

  // Testbench
  initial begin
    $dumpfile("l3q4_tb.vcd");  // VCD file for waveform
    $dumpvars(0, l3q4_tb);      // Dump variables for the simulation

    // Test all combinations of inputs
    A = 1'b0; B = 1'b0; C = 1'b0; D = 1'b0; #20;
    A = 1'b0; B = 1'b0; C = 1'b0; D = 1'b1; #20;
    A = 1'b0; B = 1'b0; C = 1'b1; D = 1'b0; #20;
    A = 1'b0; B = 1'b0; C = 1'b1; D = 1'b1; #20;
    A = 1'b0; B = 1'b1; C = 1'b0; D = 1'b0; #20;
    A = 1'b0; B = 1'b1; C = 1'b0; D = 1'b1; #20;
    A = 1'b0; B = 1'b1; C = 1'b1; D = 1'b0; #20;
    A = 1'b0; B = 1'b1; C = 1'b1; D = 1'b1; #20;
    A = 1'b1; B = 1'b0; C = 1'b0; D = 1'b0; #20;
    A = 1'b1; B = 1'b0; C = 1'b0; D = 1'b1; #20;
    A = 1'b1; B = 1'b0; C = 1'b1; D = 1'b0; #20;
    A = 1'b1; B = 1'b0; C = 1'b1; D = 1'b1; #20;
    A = 1'b1; B = 1'b1; C = 1'b0; D = 1'b0; #20;
    A = 1'b1; B = 1'b1; C = 1'b0; D = 1'b1; #20;
    A = 1'b1; B = 1'b1; C = 1'b1; D = 1'b0; #20;
    A = 1'b1; B = 1'b1; C = 1'b1; D = 1'b1; #20;

    // Display when the test is complete
    $display("Test complete");
  end
endmodule

LAB3/4/l3q4_tb.vcd
$date
	Tue Aug 12 15:05:25 2025
$end
$version
	Icarus Verilog
$end
$timescale
	1ns
$end
$scope module l3q4_tb $end
$var wire 1 ! f $end
$var reg 1 " A $end
$var reg 1 # B $end
$var reg 1 $ C $end
$var reg 1 % D $end
$scope module uut $end
$var wire 1 " A $end
$var wire 1 # B $end
$var wire 1 $ C $end
$var wire 1 % D $end
$var wire 1 & d $end
$var wire 1 ! f $end
$var wire 1 ' o1 $end
$var wire 1 ( o2 $end
$var wire 1 ) o3 $end
$upscope $end
$upscope $end
$enddefinitions $end
#0
$dumpvars
0)
1(
1'
1&
0%
0$
0#
0"
1!
$end
#20
0&
1%
#40
1&
0%
1$
#60
0&
1%
#80
0!
1)
0(
1&
0%
0$
1#
#100
1!
0)
1(
0&
1%
#120
0!
1)
0(
1&
0%
1$
#140
1!
0)
1(
0&
1%
#160
1&
0%
0$
0#
1"
#180
0!
1)
0&
0'
1%
#200
1!
0)
1&
1'
0%
1$
#220
0!
1)
0&
0'
1%
#240
0!
0(
1)
1&
1'
0%
0$
1#
#260
1(
0&
0'
1%
#280
0!
0(
1)
1&
1'
0%
1$
#300
1(
0&
0'
1%
