LAB9/Q1/JK_FF.v
// File: JK_FF.v

module JK_FF (J, K, clk, rst, Q);
    input J, K, clk, rst;
    output reg Q;

    always @(posedge clk or posedge rst)
    begin
        if (rst)
            Q <= 1'b0;
        else
        begin
            case ({J,K})
                2'b00: Q <= Q;      // No change
                2'b01: Q <= 1'b0;   // Reset
                2'b10: Q <= 1'b1;   // Set
                2'b11: Q <= ~Q;     // Toggle
            endcase
        end
    end
endmodule

LAB9/Q1/seq_cir.v
// File: seq_cir.v

module seq_cir (E, x, clk, rst, Qa, Qb);
    input E, x, clk, rst;
    output Qa, Qb;

    wire Ja, Ka, Jb, Kb;
    wire t1, t2;

    // Combinational logic for FF inputs
    assign t1 = E & x & Qb;
    assign t2 = E & ~x & ~Qb;

    assign Ja = t1 | t2;
    assign Ka = t1 | t2;
    
    assign Jb = E;
    assign Kb = E;

    // Instantiating the flip-flops
    JK_FF ffa (Ja, Ka, clk, rst, Qa);
    JK_FF ffb (Jb, Kb, clk, rst, Qb);
    
endmodule

LAB9/Q1/tb_seq_cir.v
// File: tb_seq_cir.v

`timescale 1ns/1ps

module Q1_tb;

    // Inputs
    reg E, x, clk, rst;

    // Outputs
    wire Qa, Qb;
    wire [1:0] state;

    // Connect state wires to FF outputs for easier waveform viewing
    assign state = {Qa, Qb};

    // Instantiate the Unit Under Test (UUT)
    seq_cir circ (E, x, clk, rst, Qa, Qb);

    parameter period = 10;

    // Clock generation
    initial begin
        clk = 1'b0;
        forever #(period/2) clk = ~clk;
    end

    // Stimulus generation
    initial begin
        // Initialize and dump signals for waveform viewer
        $dumpfile("Q1_tb.vcd");
        $dumpvars(0, Q1_tb);

        // Apply reset
        E = 0; x = 0; rst = 1'b1;
        #(period * 2);

        // De-assert reset and start stimulus
        rst = 1'b0;
        E = 0; x = 1;
        repeat (2) @(posedge clk);

        E = 1; x = 1;
        repeat (4) @(posedge clk);

        E = 1; x = 0;
        repeat (4) @(posedge clk);

        $finish; // End simulation
    end
    
endmodule

LAB9/Q1/Q1_tb.vcd
$date
	Tue Oct 28 01:16:18 2025
$end
$version
	Icarus Verilog
$end
$timescale
	1ps
$end
$scope module Q1_tb $end
$var wire 1 ! Qa $end
$var wire 1 " Qb $end
$var wire 2 # state [1:0] $end
$var reg 1 $ E $end
$var reg 1 % clk $end
$var reg 1 & rst $end
$var reg 1 ' x $end
$scope module circ $end
$var wire 1 ( E $end
$var wire 1 ) Ja $end
$var wire 1 * Jb $end
$var wire 1 + Ka $end
$var wire 1 , Kb $end
$var wire 1 ! Qa $end
$var wire 1 " Qb $end
$var wire 1 - clk $end
$var wire 1 . rst $end
$var wire 1 / t1 $end
$var wire 1 0 t2 $end
$var wire 1 1 x $end
$scope module ffa $end
$var wire 1 ) J $end
$var wire 1 + K $end
$var wire 1 - clk $end
$var wire 1 . rst $end
$var reg 1 2 Q $end
$upscope $end
$scope module ffb $end
$var wire 1 * J $end
$var wire 1 , K $end
$var wire 1 - clk $end
$var wire 1 . rst $end
$var reg 1 3 Q $end
$upscope $end
$upscope $end
$upscope $end
$enddefinitions $end
#0
$dumpvars
03
02
01
00
0/
1.
0-
0,
0+
0*
0)
0(
0'
1&
0%
0$
b0 #
0"
0!
$end
#5000
1%
1-
#10000
0%
0-
#15000
1%
1-
#20000
0%
0-
1'
11
0&
0.
#25000
1%
1-
#30000
0%
0-
#35000
1)
1+
1/
13
b1 #
1"
1$
1*
1,
1(
1%
1-
#40000
0%
0-
#45000
0)
0+
0/
03
0"
12
b10 #
1!
1%
1-
#50000
0%
0-
#55000
1)
1+
1/
13
b11 #
1"
1%
1-
#60000
0%
0-
#65000
0)
0+
0/
03
0"
02
b0 #
0!
1%
1-
#70000
0%
0-
#75000
13
b1 #
1"
0)
0+
00
0'
01
1%
1-
#80000
0%
0-
#85000
1)
1+
10
03
b0 #
0"
1%
1-
#90000
0%
0-
#95000
0)
0+
00
12
1!
13
b11 #
1"
1%
1-
#100000
0%
0-
#105000
1)
1+
10
03
b10 #
0"
1%
1-
#110000
0%
0-
#115000
0)
0+
00
02
0!
13
b1 #
1"
1%
1-
