LAB2/exercise 2/(A)/l2q2a.v
module l2q2a(A,B,C,D,f);
	input A,B,C,D;
	output f;
	assign f=(~B|D)&(B|C);
endmodule

LAB2/exercise 2/(A)/l2q2a_tb.v
`timescale 1ns/1ns
`include "l2q2a.v"    // Include your Verilog file

module l2q2a_tb();
  reg A, B, C, D;   // Inputs
  wire f;            // Output

  // Instantiate the l1q1 module
  l2q2a uut(A,B,C,D,f);

  // Testbench
  initial begin
    $dumpfile("l2q2a_tb.vcd");  // VCD file for waveform
    $dumpvars(0, l2q2a_tb);      // Dump variables for the simulation

    // Test all combinations of inputs
    A = 1'b0; B = 1'b0; C = 1'b0; D = 1'b0; #20;
    A = 1'b0; B = 1'b0; C = 1'b0; D = 1'b1; #20;
    A = 1'b0; B = 1'b0; C = 1'b1; D = 1'b0; #20;
    A = 1'b0; B = 1'b0; C = 1'b1; D = 1'b1; #20;
    A = 1'b0; B = 1'b1; C = 1'b0; D = 1'b0; #20;
    A = 1'b0; B = 1'b1; C = 1'b0; D = 1'b1; #20;
    A = 1'b0; B = 1'b1; C = 1'b1; D = 1'b0; #20;
    A = 1'b0; B = 1'b1; C = 1'b1; D = 1'b1; #20;
    A = 1'b1; B = 1'b0; C = 1'b0; D = 1'b0; #20;
    A = 1'b1; B = 1'b0; C = 1'b0; D = 1'b1; #20;
    A = 1'b1; B = 1'b0; C = 1'b1; D = 1'b0; #20;
    A = 1'b1; B = 1'b0; C = 1'b1; D = 1'b1; #20;
    A = 1'b1; B = 1'b1; C = 1'b0; D = 1'b0; #20;
    A = 1'b1; B = 1'b1; C = 1'b0; D = 1'b1; #20;
    A = 1'b1; B = 1'b1; C = 1'b1; D = 1'b0; #20;
    A = 1'b1; B = 1'b1; C = 1'b1; D = 1'b1; #20;

    // Display when the test is complete
    $display("Test complete");
  end
endmodule

LAB2/exercise 2/(A)/l2q2a_tb.vcd
$date
	Tue Aug  5 15:08:07 2025
$end
$version
	Icarus Verilog
$end
$timescale
	1ns
$end
$scope module l2q2a_tb $end
$var wire 1 ! f $end
$var reg 1 " A $end
$var reg 1 # B $end
$var reg 1 $ C $end
$var reg 1 % D $end
$scope module uut $end
$var wire 1 " A $end
$var wire 1 # B $end
$var wire 1 $ C $end
$var wire 1 % D $end
$var wire 1 ! f $end
$upscope $end
$upscope $end
$enddefinitions $end
#0
$dumpvars
0%
0$
0#
0"
0!
$end
#20
1%
#40
1!
0%
1$
#60
1%
#80
0!
0%
0$
1#
#100
1!
1%
#120
0!
0%
1$
#140
1!
1%
#160
0!
0%
0$
0#
1"
#180
1%
#200
1!
0%
1$
#220
1%
#240
0!
0%
0$
1#
#260
1!
1%
#280
0!
0%
1$
#300
1!
1%
