LAB3/3/l3q3.v
module l3q3(A,B,C,D,f);
input A,B,C,D;
output f;
nor(d,D,D);
nor(o1,A,d);
nor(o2,C,d);
nor(o3,o2,o1);
nor(f,o3,o3);
endmodule

LAB3/3/l3q3_tb.v
`timescale 1ns/1ns
`include "l3q3.v"

module l3q3_tb; // Add this line to define the testbench module
  reg A, B, C, D;    // Inputs
  wire f;             // Output
  l3q3 uut(A,B,C,D,f);

  // Testbench
  initial begin
    $dumpfile("l3q3_tb.vcd");  // VCD file for waveform
    $dumpvars(0, l3q3_tb);      // Dump variables for the simulation

    // Test all combinations of inputs
    A = 1'b0; B = 1'b0; C = 1'b0; D = 1'b0; #20;
    A = 1'b0; B = 1'b0; C = 1'b0; D = 1'b1; #20;
    A = 1'b0; B = 1'b0; C = 1'b1; D = 1'b0; #20;
    A = 1'b0; B = 1'b0; C = 1'b1; D = 1'b1; #20;
    A = 1'b0; B = 1'b1; C = 1'b0; D = 1'b0; #20;
    A = 1'b0; B = 1'b1; C = 1'b0; D = 1'b1; #20;
    A = 1'b0; B = 1'b1; C = 1'b1; D = 1'b0; #20;
    A = 1'b0; B = 1'b1; C = 1'b1; D = 1'b1; #20;
    A = 1'b1; B = 1'b0; C = 1'b0; D = 1'b0; #20;
    A = 1'b1; B = 1'b0; C = 1'b0; D = 1'b1; #20;
    A = 1'b1; B = 1'b0; C = 1'b1; D = 1'b0; #20;
    A = 1'b1; B = 1'b0; C = 1'b1; D = 1'b1; #20;
    A = 1'b1; B = 1'b1; C = 1'b0; D = 1'b0; #20;
    A = 1'b1; B = 1'b1; C = 1'b0; D = 1'b1; #20;
    A = 1'b1; B = 1'b1; C = 1'b1; D = 1'b0; #20;
    A = 1'b1; B = 1'b1; C = 1'b1; D = 1'b1; #20;

    // Display when the test is complete
    $display("Test complete");
  end
endmodule

LAB3/3/l3q3_tb.vcd
$date
	Tue Aug 12 15:00:02 2025
$end
$version
	Icarus Verilog
$end
$timescale
	1ns
$end
$scope module l3q3_tb $end
$var wire 1 ! f $end
$var reg 1 " A $end
$var reg 1 # B $end
$var reg 1 $ C $end
$var reg 1 % D $end
$scope module uut $end
$var wire 1 " A $end
$var wire 1 # B $end
$var wire 1 $ C $end
$var wire 1 % D $end
$var wire 1 & d $end
$var wire 1 ! f $end
$var wire 1 ' o1 $end
$var wire 1 ( o2 $end
$var wire 1 ) o3 $end
$upscope $end
$upscope $end
$enddefinitions $end
#0
$dumpvars
1)
0(
0'
1&
0%
0$
0#
0"
0!
$end
#20
1!
0)
1'
1(
0&
1%
#40
0!
1)
0'
1&
0(
0%
1$
#60
1!
0)
1'
0&
1%
#80
0!
1)
0'
1&
0(
0%
0$
1#
#100
1!
0)
1'
1(
0&
1%
#120
0!
1)
0'
1&
0(
0%
1$
#140
1!
0)
1'
0&
1%
#160
0!
1)
1&
0(
0'
0%
0$
0#
1"
#180
1!
0)
1(
0&
1%
#200
0!
1)
1&
0(
0%
1$
#220
0&
1%
#240
0!
1)
1&
0(
0%
0$
1#
#260
1!
0)
1(
0&
1%
#280
0!
1)
1&
0(
0%
1$
#300
0&
1%
