lab8/shiftreg_PL.v
module shiftreg_PL #(parameter N = 8) (clk, shift, load, Din, Pin, Dout);
input clk, shift, load;
input Din;             // Serial input for shift left
input [N-1:0] Pin;     // Parallel input
output reg [N-1:0] Dout;

always @(posedge clk)
begin
    if (shift == 1'b1)                // No change
        Dout <= Dout;
    else if (load == 1'b1)            // Parallel load
        Dout <= Pin;
    else                              // Shift left
        Dout <= {Dout[N-2:0], Din};
end
endmodule

lab8/shiftreg_PL_TB.v
`timescale 1ns/1ns
`include "shiftreg_PL.v"

module shiftreg_PL_TB();
parameter N = 8;
reg clk, shift, load, Din;
reg [N-1:0] Pin;
wire [N-1:0] Dout;

shiftreg_PL #(N) uut (clk, shift, load, Din, Pin, Dout);

initial
begin
    clk = 0;
    forever #10 clk = ~clk;
end

initial
begin
    $dumpfile("shiftreg_PL_TB.vcd");
    $dumpvars(0, shiftreg_PL_TB);

    // Initial conditions
    shift = 0; load = 1; Pin = 8'b10101010; Din = 0;
    #20;  // Load parallel data

    shift = 0; load = 0; Din = 1;  // Shift left
    #20;
    Din = 0;
    #20;

    shift = 1; load = 0;  // No change
    #20;

    shift = 0; load = 1; Pin = 8'b11110000; // Load new data
    #20;

    $display("Simulation complete");
    #50 $finish;
end
endmodule

lab8/shiftreg_PL_TB.vcd
$date
	Tue Oct  7 15:14:00 2025
$end
$version
	Icarus Verilog
$end
$timescale
	1ns
$end
$scope module shiftreg_PL_TB $end
$var wire 8 ! Dout [7:0] $end
$var reg 1 " Din $end
$var reg 8 # Pin [7:0] $end
$var reg 1 $ clk $end
$var reg 1 % load $end
$var reg 1 & shift $end
$scope module uut $end
$var wire 1 " Din $end
$var wire 8 ' Pin [7:0] $end
$var wire 1 $ clk $end
$var wire 1 % load $end
$var wire 1 & shift $end
$var reg 8 ( Dout [7:0] $end
$upscope $end
$upscope $end
$enddefinitions $end
#0
$dumpvars
bx (
b10101010 '
0&
1%
0$
b10101010 #
0"
bx !
$end
#10
b10101010 !
b10101010 (
1$
#20
0$
1"
0%
#30
b1010101 !
b1010101 (
1$
#40
0$
0"
#50
b10101010 !
b10101010 (
1$
#60
0$
1&
#70
1$
#80
0$
b11110000 #
b11110000 '
1%
0&
#90
b11110000 !
b11110000 (
1$
