lab8/shiftreg6bit.v
module shiftreg6bit(Din, clk, Dout);
input Din, clk;
output [5:0]Dout;

wire [5:0]D;

dff s1(Din, clk, D[5]);
dff s2(D[5], clk, D[4]);
dff s3(D[4], clk, D[3]);
dff s4(D[3], clk, D[2]);
dff s5(D[2], clk, D[1]);
dff s6(D[1], clk, D[0]);

assign Dout = D;

endmodule

module dff (D, Clock, Q);
input D, Clock;
output Q;
reg Q;
always @(posedge Clock)
	Q <= D;
endmodule

lab8/shiftreg6bit_TB.v
`timescale 1ns/1ns
`include "shiftreg6bit.v"

module shiftreg6bit_TB();
reg Din, clk;
wire [5:0]Dout;

shiftreg6bit s1(Din, clk, Dout);

initial
begin
	clk = 0;
	forever #10 clk = ~clk;
end

initial
begin
	$dumpfile("shiftreg6bit_TB.vcd");
	$dumpvars(0, shiftreg6bit_TB);

	Din = 1; #20;
	Din = 0; #20;
	Din = 1; #20;
	Din = 1; #20;
	Din = 0; #20;
	Din = 1; #20;

	$display("Simulation Complete");
	#50 $finish;
end
endmodule

lab8/shiftreg6bit_TB.vcd
$date
	Tue Oct  7 15:13:18 2025
$end
$version
	Icarus Verilog
$end
$timescale
	1ns
$end
$scope module shiftreg6bit_TB $end
$var wire 6 ! Dout [5:0] $end
$var reg 1 " Din $end
$var reg 1 # clk $end
$scope module s1 $end
$var wire 1 " Din $end
$var wire 6 $ Dout [5:0] $end
$var wire 1 # clk $end
$var wire 6 % D [5:0] $end
$scope module s1 $end
$var wire 1 # Clock $end
$var wire 1 " D $end
$var reg 1 & Q $end
$upscope $end
$scope module s2 $end
$var wire 1 # Clock $end
$var wire 1 ' D $end
$var reg 1 ( Q $end
$upscope $end
$scope module s3 $end
$var wire 1 # Clock $end
$var wire 1 ) D $end
$var reg 1 * Q $end
$upscope $end
$scope module s4 $end
$var wire 1 # Clock $end
$var wire 1 + D $end
$var reg 1 , Q $end
$upscope $end
$scope module s5 $end
$var wire 1 # Clock $end
$var wire 1 - D $end
$var reg 1 . Q $end
$upscope $end
$scope module s6 $end
$var wire 1 # Clock $end
$var wire 1 / D $end
$var reg 1 0 Q $end
$upscope $end
$upscope $end
$upscope $end
$enddefinitions $end
#0
$dumpvars
x0
x/
x.
x-
x,
x+
x*
x)
x(
x'
x&
bx %
bx $
0#
1"
bx !
$end
#10
1'
b1xxxxx !
b1xxxxx $
b1xxxxx %
1&
1#
#20
0#
0"
#30
1)
0'
1(
b1xxxx !
b1xxxx $
b1xxxx %
0&
1#
#40
0#
1"
#50
1'
0)
1+
1&
0(
b101xxx !
b101xxx $
b101xxx %
1*
1#
#60
0#
#70
1-
0+
1)
1,
0*
b1101xx !
b1101xx $
b1101xx %
1(
1#
#80
0#
0"
#90
0'
1+
0-
1/
0&
1*
0,
b1101x !
b1101x $
b1101x %
1.
1#
#100
0#
1"
#110
0/
1-
0)
1'
10
0.
1,
0(
b101101 !
b101101 $
b101101 %
1&
1#
#120
0#
#130
1)
0+
1/
1(
0*
1.
b110110 !
b110110 $
b110110 %
00
1#
#140
0#
#150
0-
1+
10
0,
b111011 !
b111011 $
b111011 %
1*
1#
#160
0#
#170
1-
0/
1,
b111101 !
b111101 $
b111101 %
0.
1#
