LAB6/decoder2to4.v
module decoder2to4(w, En, y);
  input [1:0] w;
  input En;
  output reg [3:0] y;

  always @(*) begin
    if (En)
      y = 4'b0001 << w;
    else
      y = 4'b0000;
  end
endmodule

LAB6/decoder3to8.v
module decoder3to8(w,En,y);
input [2:0]w;
input En;
output [7:0]y;
decoder2to4 d1(w[1:0],(En&(~w[2])),y[3:0]);
decoder2to4 d2(w[1:0],(En&w[2]),y[7:4]);
endmodule

LAB6/decoder3to8_tb.v
`timescale 1ns/1ns
`include "decoder3to8.v"
`include "decoder2to4.v"

module decoder3to8_tb();
  reg [2:0] w;
  reg En;
  wire [7:0] y;

  // Instantiate DUT
  decoder3to8 dut(w, En, y);

  initial begin
    $dumpfile("decoder3to8_tb.vcd");
    $dumpvars(0, decoder3to8_tb);

    // Enable ON – cycle through all inputs
    En = 1;
    w = 3'b000; #20;
    w = 3'b001; #20;
    w = 3'b010; #20;
    w = 3'b011; #20;
    w = 3'b100; #20;
    w = 3'b101; #20;
    w = 3'b110; #20;
    w = 3'b111; #20;

    // Enable OFF – outputs should all go zero
    En = 0;
    w = 3'b000; #20;
    w = 3'b111; #20;

    $display("Test Complete");
    $finish;
  end
endmodule

LAB6/decoder3to8_tb.vcd
$date
	Tue Sep 23 14:34:33 2025
$end
$version
	Icarus Verilog
$end
$timescale
	1ns
$end
$scope module decoder3to8_tb $end
$var wire 8 ! y [7:0] $end
$var reg 1 " En $end
$var reg 3 # w [2:0] $end
$scope module dut $end
$var wire 1 " En $end
$var wire 3 $ w [2:0] $end
$var wire 8 % y [7:0] $end
$scope module d1 $end
$var wire 1 & En $end
$var wire 2 ' w [1:0] $end
$var reg 4 ( y [3:0] $end
$upscope $end
$scope module d2 $end
$var wire 1 ) En $end
$var wire 2 * w [1:0] $end
$var reg 4 + y [3:0] $end
$upscope $end
$upscope $end
$upscope $end
$enddefinitions $end
#0
$dumpvars
b0 +
b0 *
0)
b1 (
b0 '
1&
b1 %
b0 $
b0 #
1"
b1 !
$end
#20
b10 !
b10 %
b10 (
b1 '
b1 *
b1 #
b1 $
#40
b100 !
b100 %
b100 (
b10 '
b10 *
b10 #
b10 $
#60
b1000 !
b1000 %
b1000 (
b11 '
b11 *
b11 #
b11 $
#80
0&
b0 (
b10000 !
b10000 %
b1 +
1)
b0 '
b0 *
b100 #
b100 $
#100
b100000 !
b100000 %
b10 +
b1 '
b1 *
b101 #
b101 $
#120
b1000000 !
b1000000 %
b100 +
b10 '
b10 *
b110 #
b110 $
#140
b10000000 !
b10000000 %
b1000 +
b11 '
b11 *
b111 #
b111 $
#160
b0 !
b0 %
b0 +
b0 '
b0 *
0)
b0 #
b0 $
0"
#180
b11 '
b11 *
b111 #
b111 $
