LAB6/decoder3to8_for.v
module decoder3to8_for(w,En,y);
input [2:0]w;
input En;
output reg [7:0]y;
integer k;
always @(*) begin
    for(k=0;k<8;k=k+1) begin
        if((w==k)&&(En==1))
            y[k]=1;
        else
            y[k]=0;
    end
end
endmodule

LAB6/decoder4to16.v
module decoder4to16(w,En,y);
input [3:0]w;
input En;
output [15:0]y;

decoder3to8_for d1(w[2:0],(En&(~w[3])),y[7:0]);
decoder3to8_for d2(w[2:0],(En&(w[3])),y[15:8]);

endmodule

LAB6/decoder4to16_tb.v
`timescale 1ns/1ns
`include "decoder3to8_for.v"
`include "decoder4to16.v"

module decoder4to16_tb;
    reg [3:0] w;
    reg En;
    wire [15:0] y;

    // Instantiate DUT
    decoder4to16 uut(w, En, y);

    integer i, j;

    initial begin
        $dumpfile("decoder4to16_tb.vcd");
        $dumpvars(0, decoder4to16_tb);

        // Loop through all possible En and w combinations
        for (j = 0; j < 2; j = j + 1) begin  // En = 0,1
            En = j;
            for (i = 0; i < 16; i = i + 1) begin  // w = 0..15
                w = i;
                #10;  // small delay to observe output
                $display("Time=%0t | En=%b | w=%b (%0d) | y=%016b",
                          $time, En, w, w, y);
            end
        end

        $finish;
    end
endmodule

LAB6/decoder4to16_tb.vcd
$date
	Tue Sep 23 14:50:48 2025
$end
$version
	Icarus Verilog
$end
$timescale
	1ns
$end
$scope module decoder4to16_tb $end
$var wire 16 ! y [15:0] $end
$var reg 1 " En $end
$var reg 4 # w [3:0] $end
$var integer 32 $ i [31:0] $end
$var integer 32 % j [31:0] $end
$scope module uut $end
$var wire 1 " En $end
$var wire 4 & w [3:0] $end
$var wire 16 ' y [15:0] $end
$scope module d1 $end
$var wire 1 ( En $end
$var wire 3 ) w [2:0] $end
$var reg 8 * y [7:0] $end
$var integer 32 + k [31:0] $end
$upscope $end
$scope module d2 $end
$var wire 1 , En $end
$var wire 3 - w [2:0] $end
$var reg 8 . y [7:0] $end
$var integer 32 / k [31:0] $end
$upscope $end
$upscope $end
$upscope $end
$enddefinitions $end
#0
$dumpvars
b1000 /
b0 .
b0 -
0,
b1000 +
b0 *
b0 )
0(
b0 '
b0 &
b0 %
b0 $
b0 #
0"
b0 !
$end
#10
b1000 +
b1000 /
b1 )
b1 -
b1 #
b1 &
b1 $
#20
b1000 +
b1000 /
b10 )
b10 -
b10 #
b10 &
b10 $
#30
b1000 +
b1000 /
b11 )
b11 -
b11 #
b11 &
b11 $
#40
b1000 +
b1000 /
b100 )
b100 -
b100 #
b100 &
b100 $
#50
b1000 +
b1000 /
b101 )
b101 -
b101 #
b101 &
b101 $
#60
b1000 +
b1000 /
b110 )
b110 -
b110 #
b110 &
b110 $
#70
b1000 +
b1000 /
b111 )
b111 -
b111 #
b111 &
b111 $
#80
b1000 +
b1000 /
b0 )
b0 -
b1000 #
b1000 &
b1000 $
#90
b1000 +
b1000 /
b1 )
b1 -
b1001 #
b1001 &
b1001 $
#100
b1000 +
b1000 /
b10 )
b10 -
b1010 #
b1010 &
b1010 $
#110
b1000 +
b1000 /
b11 )
b11 -
b1011 #
b1011 &
b1011 $
#120
b1000 +
b1000 /
b100 )
b100 -
b1100 #
b1100 &
b1100 $
#130
b1000 +
b1000 /
b101 )
b101 -
b1101 #
b1101 &
b1101 $
#140
b1000 +
b1000 /
b110 )
b110 -
b1110 #
b1110 &
b1110 $
#150
b1000 +
b1000 /
b111 )
b111 -
b1111 #
b1111 &
b1111 $
#160
b1 *
1(
b1000 +
b1 !
b1 '
b0 .
b1000 /
b0 )
b0 -
0,
b0 #
b0 &
1"
b1 %
b0 $
#170
b10 !
b10 '
b10 *
b1000 +
b1000 /
b1 )
b1 -
b1 #
b1 &
b1 $
#180
b100 !
b100 '
b100 *
b1000 +
b1000 /
b10 )
b10 -
b10 #
b10 &
b10 $
#190
b1000 !
b1000 '
b1000 *
b1000 +
b1000 /
b11 )
b11 -
b11 #
b11 &
b11 $
#200
b10000 !
b10000 '
b10000 *
b1000 +
b1000 /
b100 )
b100 -
b100 #
b100 &
b100 $
#210
b100000 !
b100000 '
b100000 *
b1000 +
b1000 /
b101 )
b101 -
b101 #
b101 &
b101 $
#220
b1000000 !
b1000000 '
b1000000 *
b1000 +
b1000 /
b110 )
b110 -
b110 #
b110 &
b110 $
#230
b10000000 !
b10000000 '
b10000000 *
b1000 +
b1000 /
b111 )
b111 -
b111 #
b111 &
b111 $
#240
0(
b0 *
b1000 +
b100000000 !
b100000000 '
b1 .
b1000 /
1,
b0 )
b0 -
b1000 #
b1000 &
b1000 $
#250
b1000 +
b1000000000 !
b1000000000 '
b10 .
b1000 /
b1 )
b1 -
b1001 #
b1001 &
b1001 $
#260
b1000 +
b10000000000 !
b10000000000 '
b100 .
b1000 /
b10 )
b10 -
b1010 #
b1010 &
b1010 $
#270
b1000 +
b100000000000 !
b100000000000 '
b1000 .
b1000 /
b11 )
b11 -
b1011 #
b1011 &
b1011 $
#280
b1000 +
b1000000000000 !
b1000000000000 '
b10000 .
b1000 /
b100 )
b100 -
b1100 #
b1100 &
b1100 $
#290
b1000 +
b10000000000000 !
b10000000000000 '
b100000 .
b1000 /
b101 )
b101 -
b1101 #
b1101 &
b1101 $
#300
b1000 +
b100000000000000 !
b100000000000000 '
b1000000 .
b1000 /
b110 )
b110 -
b1110 #
b1110 &
b1110 $
#310
b1000 +
b1000000000000000 !
b1000000000000000 '
b10000000 .
b1000 /
b111 )
b111 -
b1111 #
b1111 &
b1111 $
#320
b10 %
b10000 $
