LAB6/pe16to4.v
module pe16to4(
    input  [15:0] d,    
    output reg [3:0] y, 
    output reg valid    
);

    integer i;
    reg found;

    always @(*) begin
        valid = 0;
        y = 4'b0000;
        found = 0;
        for (i = 15; i >= 0; i = i - 1) begin
            if (!found && d[i]) begin
                y = i[3:0]; 
                valid = 1;
                found = 1;   
            end
        end
    end

endmodule

LAB6/pe16to4_tb.v
`timescale 1ns/1ns
`include "pe16to4.v"

module pe16to4_tb();
    reg [15:0] d;
    wire [3:0] y;
    wire valid;
    pe16to4 uut (
        .d(d),
        .y(y),
        .valid(valid)
    );

    integer i;

    initial begin
        $dumpfile("pe16to4_tb.vcd");
        $dumpvars(0, pe16to4_tb);
        $display("Testing one-hot inputs (single 1 at a time):");
        for (i = 0; i < 16; i = i + 1) begin
            d = 16'b0;
            d[i] = 1'b1;
            #10;
            $display("d=%b, y=%b, valid=%b", d, y, valid);
        end

        $display("\nTesting multiple-bit inputs to verify priority:");

        d = 16'b0000_0000_0000_1010; 
        #10; $display("d=%b, y=%b, valid=%b", d, y, valid);

        d = 16'b1000_0000_0000_0011; 
        #10; $display("d=%b, y=%b, valid=%b", d, y, valid);

        d = 16'b0000_0000_0000_0000;
        #10; $display("d=%b, y=%b, valid=%b", d, y, valid);

        $display("\nTest Complete");
        $finish;
    end
endmodule

LAB6/pe16to4_tb.vcd
$date
	Tue Sep 23 15:15:46 2025
$end
$version
	Icarus Verilog
$end
$timescale
	1ns
$end
$scope module pe16to4_tb $end
$var wire 4 ! y [3:0] $end
$var wire 1 " valid $end
$var reg 16 # d [15:0] $end
$var integer 32 $ i [31:0] $end
$scope module uut $end
$var wire 16 % d [15:0] $end
$var reg 1 & found $end
$var reg 1 " valid $end
$var reg 4 ' y [3:0] $end
$var integer 32 ( i [31:0] $end
$upscope $end
$upscope $end
$enddefinitions $end
#0
$dumpvars
b11111111111111111111111111111111 (
b0 '
1&
b1 %
b0 $
b1 #
1"
b0 !
$end
#10
b1 !
b1 '
b11111111111111111111111111111111 (
1&
1"
b10 #
b10 %
b1 $
#20
b11111111111111111111111111111111 (
1&
b10 !
b10 '
1"
b100 #
b100 %
b10 $
#30
b11111111111111111111111111111111 (
1&
b11 !
b11 '
1"
b1000 #
b1000 %
b11 $
#40
b11111111111111111111111111111111 (
1&
b100 !
b100 '
1"
b10000 #
b10000 %
b100 $
#50
b11111111111111111111111111111111 (
1&
b101 !
b101 '
1"
b100000 #
b100000 %
b101 $
#60
b11111111111111111111111111111111 (
1&
b110 !
b110 '
1"
b1000000 #
b1000000 %
b110 $
#70
b11111111111111111111111111111111 (
1&
b111 !
b111 '
1"
b10000000 #
b10000000 %
b111 $
#80
b11111111111111111111111111111111 (
1&
b1000 !
b1000 '
1"
b100000000 #
b100000000 %
b1000 $
#90
b11111111111111111111111111111111 (
1&
b1001 !
b1001 '
1"
b1000000000 #
b1000000000 %
b1001 $
#100
b11111111111111111111111111111111 (
1&
b1010 !
b1010 '
1"
b10000000000 #
b10000000000 %
b1010 $
#110
b11111111111111111111111111111111 (
1&
b1011 !
b1011 '
1"
b100000000000 #
b100000000000 %
b1011 $
#120
b11111111111111111111111111111111 (
1&
b1100 !
b1100 '
1"
b1000000000000 #
b1000000000000 %
b1100 $
#130
b11111111111111111111111111111111 (
1&
b1101 !
b1101 '
1"
b10000000000000 #
b10000000000000 %
b1101 $
#140
b11111111111111111111111111111111 (
1&
b1110 !
b1110 '
1"
b100000000000000 #
b100000000000000 %
b1110 $
#150
b11111111111111111111111111111111 (
1&
b1111 !
b1111 '
1"
b1000000000000000 #
b1000000000000000 %
b1111 $
#160
b11111111111111111111111111111111 (
1&
b11 !
b11 '
1"
b1010 #
b1010 %
b10000 $
#170
b11111111111111111111111111111111 (
1&
b1111 !
b1111 '
1"
b1000000000000011 #
b1000000000000011 %
#180
b11111111111111111111111111111111 (
0&
b0 !
b0 '
0"
b0 #
b0 %
