lab1/EXERCISE 2/2.1/l1q2.v
module l1q2(a,b,c,d,f,g);
  input a,b,c,d;
  output f,g;
  wire o1;
  
  nand(o1,a,b);    // NAND gate
  xor(f,o1,c,d);   // XOR gate
  nor(g,b,c,d);    // NOR gate
endmodule

lab1/EXERCISE 2/2.1/l1q2_tb.v
`timescale 1ns/1ns
`include "l1q2.v"

module l1q2_tb;
  reg a, b, c, d;  // Inputs
  wire f, g;       // Outputs

  // Instantiate the l1q2 module
  l1q2 uut (
    .a(a),
    .b(b),
    .c(c),
    .d(d),
    .f(f),
    .g(g)
  );

  // Testbench
  initial begin
    $dumpfile("l1q2_tb.vcd");  // VCD file for waveform
    $dumpvars(0, l1q2_tb);      // Dump variables for the simulation

    // Test all combinations of inputs
    a = 0; b = 0; c = 0; d = 0; #20;
    a = 0; b = 0; c = 0; d = 1; #20;
    a = 0; b = 0; c = 1; d = 0; #20;
    a = 0; b = 0; c = 1; d = 1; #20;
    a = 0; b = 1; c = 0; d = 0; #20;
    a = 0; b = 1; c = 0; d = 1; #20;
    a = 0; b = 1; c = 1; d = 0; #20;
    a = 0; b = 1; c = 1; d = 1; #20;
    a = 1; b = 0; c = 0; d = 0; #20;
    a = 1; b = 0; c = 0; d = 1; #20;
    a = 1; b = 0; c = 1; d = 0; #20;
    a = 1; b = 0; c = 1; d = 1; #20;
    a = 1; b = 1; c = 0; d = 0; #20;
    a = 1; b = 1; c = 0; d = 1; #20;
    a = 1; b = 1; c = 1; d = 0; #20;
    a = 1; b = 1; c = 1; d = 1; #20;

    $display("Test complete");
  end
endmodule

lab1/EXERCISE 2/2.1/l1q2_tb.vcd
$date
	Tue Jul 29 15:26:08 2025
$end
$version
	Icarus Verilog
$end
$timescale
	1ns
$end
$scope module l1q2_tb $end
$var wire 1 ! g $end
$var wire 1 " f $end
$var reg 1 # a $end
$var reg 1 $ b $end
$var reg 1 % c $end
$var reg 1 & d $end
$scope module uut $end
$var wire 1 # a $end
$var wire 1 $ b $end
$var wire 1 % c $end
$var wire 1 & d $end
$var wire 1 " f $end
$var wire 1 ! g $end
$var wire 1 ' o1 $end
$upscope $end
$upscope $end
$enddefinitions $end
#0
$dumpvars
1'
0&
0%
0$
0#
1"
1!
$end
#20
0"
0!
1&
#40
0&
1%
#60
1"
1&
#80
0&
0%
1$
#100
0"
1&
#120
0&
1%
#140
1"
1&
#160
1!
0&
0%
0$
1#
#180
0"
0!
1&
#200
0&
1%
#220
1"
1&
#240
0"
0'
0&
0%
1$
#260
1"
1&
#280
0&
1%
#300
0"
1&
