LAB7/neg_T_ff.v
module neg_T_ff (T, Clock, Resetn, Q);
    input T, Clock, Resetn;
    output Q;
    reg Q;

    initial Q = 1'b0;

    always @(negedge Clock or negedge Resetn)
        if (!Resetn)
            Q <= 1'b0;
        else if (T)
            Q <= ~Q;
endmodule

LAB7/neg_T_ff_tb.v
`timescale 1ns/1ns
`include "neg_T_ff.v"

module neg_T_ff_tb();
    reg T, Clock, Resetn;
    wire Q;

    neg_T_ff dut(T, Clock, Resetn, Q);

    initial begin
        Clock = 0;
        forever #20 Clock = ~Clock;
    end

    initial begin
        $dumpfile("neg_T_ff_tb.vcd");
        $dumpvars(0, neg_T_ff_tb);

        Resetn = 0; T = 1;
        #30;
        Resetn = 1;
        #20;
        
        T = 1;
        #80; 

        T = 0;
        #80;

        T = 1;
        #40;

        Resetn = 0;
        #30;
        Resetn = 1;
        #20;
        
        $display("Test complete");
        $finish;
    end
endmodule

LAB7/neg_T_ff_tb.vcd
$date
	Tue Sep 30 14:33:31 2025
$end
$version
	Icarus Verilog
$end
$timescale
	1ns
$end
$scope module neg_T_ff_tb $end
$var wire 1 ! Q $end
$var reg 1 " Clock $end
$var reg 1 # Resetn $end
$var reg 1 $ T $end
$scope module dut $end
$var wire 1 " Clock $end
$var wire 1 # Resetn $end
$var wire 1 $ T $end
$var reg 1 ! Q $end
$upscope $end
$upscope $end
$enddefinitions $end
#0
$dumpvars
1$
0#
0"
0!
$end
#20
1"
#30
1#
#40
1!
0"
#60
1"
#80
0!
0"
#100
1"
#120
1!
0"
#130
0$
#140
1"
#160
0"
#180
1"
#200
0"
#210
1$
#220
1"
#240
0!
0"
#250
0#
#260
1"
#280
1!
0"
1#
