LAB7/neg_SR_ff.v
module neg_SR_ff (S, R, Clock, Resetn, Q);
    input S, R, Clock, Resetn;
    output Q;
    reg Q;

    initial Q = 1'b0;

    always @(negedge Clock)
        if (!Resetn)
            Q <= 1'b0;
        else
            case ({S,R})
                2'b00: Q <= Q;
                2'b01: Q <= 1'b0;
                2'b10: Q <= 1'b1;
                2'b11: Q <= 1'bx; // Invalid state
            endcase
endmodule

LAB7/neg_SR_ff_tb.v
`timescale 1ns/1ns
`include "neg_SR_ff.v"

module neg_SR_ff_tb();
    reg S, R, Clock, Resetn;
    wire Q;

    neg_SR_ff dut(S, R, Clock, Resetn, Q);

    initial begin
        Clock = 0;
        forever #20 Clock = ~Clock;
    end

    initial begin
        $dumpfile("neg_SR_ff_tb.vcd");
        $dumpvars(0, neg_SR_ff_tb);

        Resetn = 0; S = 1; R = 1;
        #45;
        Resetn = 1;

        S = 0; R = 0;
        #40;

        S = 1; R = 0;
        #40;
        
        S = 0; R = 0;
        #40;

        S = 0; R = 1;
        #40;

        S = 1; R = 1;
        #40;
        
        $display("Test complete");
        $finish;
    end
endmodule

LAB7/neg_SR_ff_tb.vcd
$date
	Tue Sep 30 14:48:47 2025
$end
$version
	Icarus Verilog
$end
$timescale
	1ns
$end
$scope module neg_SR_ff_tb $end
$var wire 1 ! Q $end
$var reg 1 " Clock $end
$var reg 1 # R $end
$var reg 1 $ Resetn $end
$var reg 1 % S $end
$scope module dut $end
$var wire 1 " Clock $end
$var wire 1 # R $end
$var wire 1 $ Resetn $end
$var wire 1 % S $end
$var reg 1 ! Q $end
$upscope $end
$upscope $end
$enddefinitions $end
#0
$dumpvars
1%
0$
1#
0"
0!
$end
#20
1"
#40
0"
#45
0#
0%
1$
#60
1"
#80
0"
#85
1%
#100
1"
#120
1!
0"
#125
0%
#140
1"
#160
0"
#165
1#
#180
1"
#200
0!
0"
#205
1%
#220
1"
#240
x!
0"
