LAB7/pos_JK_ff.v
module pos_JK_ff (J, K, Clock, Reset, Q);
    input J, K, Clock, Reset;
    output Q;
    reg Q;

    initial Q = 1'b0;

    always @(posedge Clock)
        if (Reset)
            Q <= 1'b0;
        else
            case ({J,K})
                2'b00: Q <= Q;
                2'b01: Q <= 1'b0;
                2'b10: Q <= 1'b1;
                2'b11: Q <= ~Q;
            endcase
endmodule

LAB7/pos_JK_ff_tb.v
`timescale 1ns/1ns
`include "pos_JK_ff.v"

module pos_JK_ff_tb();
    reg J, K, Clock, Reset;
    wire Q;

    pos_JK_ff dut(J, K, Clock, Reset, Q);

    initial begin
        Clock = 0;
        forever #20 Clock = ~Clock;
    end

    initial begin
        $dumpfile("pos_JK_ff_tb.vcd");
        $dumpvars(0, pos_JK_ff_tb);

        Reset = 1; J = 1; K = 1;
        #45;
        Reset = 0;

        J = 0; K = 0;
        #40;

        J = 1; K = 0;
        #40;
        
        J = 0; K = 1;
        #40;

        J = 1; K = 1;
        #80;
        
        $display("Test complete");
        $finish;
    end
endmodule

LAB7/pos_JK_ff_tb.vcd
$date
	Tue Sep 30 14:44:18 2025
$end
$version
	Icarus Verilog
$end
$timescale
	1ns
$end
$scope module pos_JK_ff_tb $end
$var wire 1 ! Q $end
$var reg 1 " Clock $end
$var reg 1 # J $end
$var reg 1 $ K $end
$var reg 1 % Reset $end
$scope module dut $end
$var wire 1 " Clock $end
$var wire 1 # J $end
$var wire 1 $ K $end
$var wire 1 % Reset $end
$var reg 1 ! Q $end
$upscope $end
$upscope $end
$enddefinitions $end
#0
$dumpvars
1%
1$
1#
0"
0!
$end
#20
1"
#40
0"
#45
0$
0#
0%
#60
1"
#80
0"
#85
1#
#100
1!
1"
#120
0"
#125
1$
0#
#140
0!
1"
#160
0"
#165
1#
#180
1!
1"
#200
0"
#220
0!
1"
