LAB7/pos_D.v
module pos_D (D, Clock, Reset, Q);
    input D, Clock, Reset;
    output Q;
    reg Q;

    always @(posedge Clock or posedge Reset)
        if (Reset)
            Q <= 1'b0;
        else
            Q <= D;
endmodule

LAB7/pos_D_tb.v
`timescale 1ns/1ns
`include "pos_D.v" // Name of the Verilog design file

module pos_D_tb();
    // Inputs to the DUT are declared as reg
    reg D, Clock, Reset;
    // Output from the DUT is declared as wire
    wire Q;

    // Instantiation of the module
    pos_D f1(D, Clock, Reset, Q);

    // Clock generation block
    initial begin
        Clock = 0;
        // Generate a clock with a 40ns period
        forever #20 Clock = ~Clock;
    end

    // Stimulus block
    initial begin
        // Setup waveform dumping
        $dumpfile("pos_D_tb.vcd");
        $dumpvars(0, pos_D_tb);

        // Test sequence
        D = 1; Reset = 1; // Start with reset asserted
        #30;
        Reset = 0; // De-assert reset
        #20;
        D = 0;
        #40;
        D = 1;
        #40;
        Reset = 1; // Assert reset again asynchronously
        #30;
        Reset = 0;
        #20;
        
        $display("Test complete");
        $finish; // End the simulation
    end
endmodule

LAB7/pos_D_tb.vcd
$date
	Tue Sep 30 14:30:58 2025
$end
$version
	Icarus Verilog
$end
$timescale
	1ns
$end
$scope module pos_D_tb $end
$var wire 1 ! Q $end
$var reg 1 " Clock $end
$var reg 1 # D $end
$var reg 1 $ Reset $end
$scope module f1 $end
$var wire 1 " Clock $end
$var wire 1 # D $end
$var wire 1 $ Reset $end
$var reg 1 ! Q $end
$upscope $end
$upscope $end
$enddefinitions $end
#0
$dumpvars
1$
1#
0"
0!
$end
#20
1"
#30
0$
#40
0"
#50
0#
#60
1"
#80
0"
#90
1#
#100
1!
1"
#120
0"
#130
0!
1$
#140
1"
#160
0"
0$
#180
1!
1"
